dt_pygnmi-0.8.13.data/scripts/pygnmicli
pygnmi/__init__.py
pygnmi/arg_parser.py
pygnmi/client.py
pygnmi/create_gnmi_extension.py
pygnmi/create_gnmi_path.py
pygnmi/tools.py
pygnmi/artefacts/messages.py
pygnmi/spec/v080/gnmi_ext_pb2.py
pygnmi/spec/v080/gnmi_pb2.py
pygnmi/spec/v080/gnmi_pb2_grpc.py
dt_pygnmi-0.8.13.dist-info/LICENSE.txt
dt_pygnmi-0.8.13.dist-info/METADATA
dt_pygnmi-0.8.13.dist-info/WHEEL
dt_pygnmi-0.8.13.dist-info/top_level.txt
dt_pygnmi-0.8.13.dist-info/RECORD
