Metadata-Version: 2.1
Name: dt-pygnmi
Version: 0.8.13
Summary: Pure Python gNMI client to manage network functions and collect telemetry.
Home-page: https://github.com/akarneliuk/pygnmi
Download-URL: https://github.com/akarneliuk/pygnmi/archive/v0.8.13.tar.gz
Author: Anton Karneliuk
Author-email: anton@karneliuk.com
License: bsd-3-clause
Keywords: gnmi,automation,grpc,network
Classifier: Development Status :: 5 - Production/Stable
Classifier: Intended Audience :: Developers
Classifier: Intended Audience :: System Administrators
Classifier: Intended Audience :: Telecommunications Industry
Classifier: Operating System :: OS Independent
Classifier: Topic :: System :: Networking
Classifier: License :: OSI Approved :: BSD License
Classifier: Programming Language :: Python :: 3
Classifier: Programming Language :: Python :: 3.7
Classifier: Programming Language :: Python :: 3.8
Classifier: Programming Language :: Python :: 3.9
Classifier: Programming Language :: Python :: 3.10
Classifier: Programming Language :: Python :: 3.11
License-File: LICENSE.txt
Requires-Dist: grpcio
Requires-Dist: protobuf
Requires-Dist: cryptography
Requires-Dist: dictdiffer
